LICENSE
MANIFEST.in
README.md
setup.cfg
setup.py
partharjun/__init__.py
partharjun/config.py
partharjun.egg-info/PKG-INFO
partharjun.egg-info/SOURCES.txt
partharjun.egg-info/dependency_links.txt
partharjun.egg-info/requires.txt
partharjun.egg-info/top_level.txt
partharjun/Clients/__init__.py
partharjun/Clients/client.py
partharjun/Clients/pytgcalls.py
partharjun/blacklist/__init__.py
partharjun/blacklist/support.py
partharjun/button/__init__.py
partharjun/button/button.py
partharjun/extra/__init__.py
partharjun/extra/hosted.py
partharjun/help/__init__.py
partharjun/help/help.py
partharjun/helper/__init__.py
partharjun/helper/basic.py
partharjun/helper/call.py
partharjun/helper/data.py
partharjun/helper/ekankth.py
partharjun/helper/goblok.py
partharjun/helper/hacking.py
partharjun/helper/inline.py
partharjun/helper/interval.py
partharjun/helper/parser.py
partharjun/helper/repo.py
partharjun/helper/sticker.py
partharjun/helper/tools.py
partharjun/helper/utility.py
partharjun/helper/what.py
partharjun/methods/__init__.py
partharjun/methods/queue.py
partharjun/py_trans/__init__.py
partharjun/py_trans/async_translator.py
partharjun/py_trans/errors.py
partharjun/py_trans/language_codes.py
partharjun/py_trans/translator.py
partharjun/pyrogram/__init__.py
partharjun/pyrogram/_wrappers.py
partharjun/pyrogram/func.py
partharjun/pyrogram/misc.py
partharjun/pyrogram/sections.py
partharjun/pyrogram/toolbot.py
partharjun/pyrogram/tools.py