Metadata-Version: 2.1
Name: partharjun
Version: 0.1.15
Summary: Primarch Userbot 
Home-page: https://blackweb.tech
Author: Arjunarth
Author-email: arjunarth@gmail.com
License: MIT
Classifier: License :: OSI Approved :: MIT License
Classifier: Programming Language :: Python
Classifier: Programming Language :: Python :: 3
Classifier: Programming Language :: Python :: 3.6
Classifier: Programming Language :: Python :: 3.7
Classifier: Programming Language :: Python :: 3.8
Classifier: Programming Language :: Python :: Implementation :: CPython
Classifier: Programming Language :: Python :: Implementation :: PyPy
Requires-Python: ~=3.8
License-File: LICENSE
